pysidian/__init__.py
pysidian/cli.py
pysidian/core/base.py
pysidian/core/vault.py
pysidian/core/workplace.py
pysidian/data/__init__.py
pysidian/data/sample_plugin.zip
pysidian/utils/hash.py
pysidian/utils/misc.py
pysidian/utils/obsidian_vault_init.py
pysidian-3.2.1.dist-info/LICENSE
pysidian-3.2.1.dist-info/METADATA
pysidian-3.2.1.dist-info/WHEEL
pysidian-3.2.1.dist-info/entry_points.txt
pysidian-3.2.1.dist-info/top_level.txt
pysidian-3.2.1.dist-info/RECORD
