Metadata-Version: 2.1
Name: pysidian
Version: 3.2.1
Summary: A CLI tool written in Python intended for managing obsidian plugin deployments and development
Author: ZackaryW
Requires-Python: >=3.10
License-File: LICENSE
Requires-Dist: click
Requires-Dist: toml
Requires-Dist: packaging
Requires-Dist: psutil
Requires-Dist: sioDict
Requires-Dist: orjson
Requires-Dist: uuid
